theorytoolkit/__init__.py
theorytoolkit/main.py
theorytoolkit-1.0.2.dist-info/METADATA
theorytoolkit-1.0.2.dist-info/WHEEL
theorytoolkit-1.0.2.dist-info/top_level.txt
theorytoolkit-1.0.2.dist-info/RECORD
