Metadata-Version: 2.1
Name: theorytoolkit
Version: 1.0.2
Summary: This package refers to the topic of automata theory, which includes DFA, NDFA, Mealy machines, and Moore machines.
Author: Mohammed Varaliya
Author-email: <mail@neuralnine.com>
Keywords: python,DFA,NDFA,Mealy machines,Moore machines,Automata,Theory of Computation
Classifier: Development Status :: 1 - Planning
Classifier: Intended Audience :: Developers
Classifier: Programming Language :: Python :: 3
Classifier: Operating System :: Unix
Classifier: Operating System :: MacOS :: MacOS X
Classifier: Operating System :: Microsoft :: Windows
